payments_przelewy24/__init__.py
payments_przelewy24/api.py
payments_przelewy24/config.py
payments_przelewy24/forms.py
payments_przelewy24/provider.py
django_payments_przelewy24-0.1.7.dist-info/AUTHORS.rst
django_payments_przelewy24-0.1.7.dist-info/LICENSE
django_payments_przelewy24-0.1.7.dist-info/METADATA
django_payments_przelewy24-0.1.7.dist-info/WHEEL
django_payments_przelewy24-0.1.7.dist-info/top_level.txt
django_payments_przelewy24-0.1.7.dist-info/RECORD
