Metadata-Version: 2.1
Name: django-payments-przelewy24
Version: 0.1.7
Summary: Your project description goes here
Home-page: https://github.com/ar4s/django-payments-przelewy24
Author: django-payments-przelewy24
Author-email: arkadiusz.adamski@gmail.com
License: MIT
Keywords: django-payments-przelewy24
Platform: UNKNOWN
Classifier: Development Status :: 3 - Alpha
Classifier: Framework :: Django :: 2.1
Classifier: Framework :: Django :: 3.1
Classifier: Intended Audience :: Developers
Classifier: License :: OSI Approved :: BSD License
Classifier: Natural Language :: English
Classifier: Programming Language :: Python :: 3
Classifier: Programming Language :: Python :: 3.8
Requires-Dist: django-payments (>=0.12.0)
